gitignore-0.0.6.dist-info/top_level.txt
gitignore-0.0.6.dist-info/WHEEL
gitignore-0.0.6.dist-info/entry_points.txt
gitignore-0.0.6.dist-info/metadata.json
gitignore-0.0.6.dist-info/METADATA
gitignore-0.0.6.dist-info/RECORD
gitignore-0.0.6.dist-info/DESCRIPTION.rst
gitignore/gitignore.py
gitignore/__init__.py
gitignore/data/Gcov.gitignore
gitignore/data/Symfony.gitignore
gitignore/data/Android.gitignore
gitignore/data/C.gitignore
gitignore/data/Leiningen.gitignore
gitignore/data/Laravel.gitignore
gitignore/data/ROS.gitignore
gitignore/data/ArchLinuxPackages.gitignore
gitignore/data/Packer.gitignore
gitignore/data/Typo3.gitignore
gitignore/data/Ada.gitignore
gitignore/data/Gradle.gitignore
gitignore/data/EPiServer.gitignore
gitignore/data/Eagle.gitignore
gitignore/data/ForceDotCom.gitignore
gitignore/data/ExtJs.gitignore
gitignore/data/VVVV.gitignore
gitignore/data/Node.gitignore
gitignore/data/DM.gitignore
gitignore/data/SugarCRM.gitignore
gitignore/data/Scrivener.gitignore
gitignore/data/OpenCart.gitignore
gitignore/data/R.gitignore
gitignore/data/Stella.gitignore
gitignore/data/Opa.gitignore
gitignore/data/Sdcc.gitignore
gitignore/data/Rails.gitignore
gitignore/data/Drupal.gitignore
gitignore/data/Unity.gitignore
gitignore/data/Idris.gitignore
gitignore/data/LabVIEW.gitignore
gitignore/data/TurboGears2.gitignore
gitignore/data/Finale.gitignore
gitignore/data/TeX.gitignore
gitignore/data/Clojure.gitignore
gitignore/data/Objective-C.gitignore
gitignore/data/IGORPro.gitignore
gitignore/data/Jekyll.gitignore
gitignore/data/Yii.gitignore
gitignore/data/Scala.gitignore
gitignore/data/Grails.gitignore
gitignore/data/Autotools.gitignore
gitignore/data/OCaml.gitignore
gitignore/data/Lithium.gitignore
gitignore/data/Umbraco.gitignore
gitignore/data/GWT.gitignore
gitignore/data/Fortran.gitignore
gitignore/data/Actionscript.gitignore
gitignore/data/Plone.gitignore
gitignore/data/Delphi.gitignore
gitignore/data/Nim.gitignore
gitignore/data/Swift.gitignore
gitignore/data/Coq.gitignore
gitignore/data/ZendFramework.gitignore
gitignore/data/Jython.gitignore
gitignore/data/FuelPHP.gitignore
gitignore/data/SketchUp.gitignore
gitignore/data/SymphonyCMS.gitignore
