Metadata-Version: 2.0
Name: gitignore
Version: 0.0.6
Summary: gitignore command generates .gitingore files from the command line.
Home-page: http://github.com/vicky002/L-Commands
Author: Vikesh Tiwari
Author-email: tvicky002@gmail.com
License: MIT
Keywords: gitignore,git,github,command line,cli
Platform: UNKNOWN
Requires-Dist: docopt (>=0.6.2)
